claude_bedrock_setup-0.2.0.dist-info/licenses/LICENSE
claude_setup/__init__.py
claude_setup/_version.py
claude_setup/auth_checker.py
claude_setup/aws_client.py
claude_setup/cli.py
claude_setup/config_manager.py
claude_setup/gitignore_manager.py
claude_setup/py.typed
claude_bedrock_setup-0.2.0.dist-info/METADATA
claude_bedrock_setup-0.2.0.dist-info/WHEEL
claude_bedrock_setup-0.2.0.dist-info/entry_points.txt
claude_bedrock_setup-0.2.0.dist-info/top_level.txt
claude_bedrock_setup-0.2.0.dist-info/RECORD
