Metadata-Version: 2.4
Name: claude-bedrock-setup
Version: 0.2.0
Summary: CLI tool to configure Claude Code for AWS Bedrock
Home-page: https://github.com/christensen143/claude-bedrock-setup
Author: Chris Christensen
Author-email: Chris Christensen <chris@nexusweblabs.com>
Maintainer-email: Chris Christensen <chris@nexusweblabs.com>
License: MIT License
Project-URL: Homepage, https://github.com/christensen143/claude-bedrock-setup
Project-URL: Bug Tracker, https://github.com/christensen143/claude-bedrock-setup/issues
Project-URL: Documentation, https://github.com/christensen143/claude-bedrock-setup#readme
Project-URL: Source Code, https://github.com/christensen143/claude-bedrock-setup
Project-URL: Changelog, https://github.com/christensen143/claude-bedrock-setup/blob/main/CHANGELOG.md
Keywords: claude,anthropic,aws,bedrock,cli,configuration,setup,ai,llm,chatbot
Classifier: Development Status :: 4 - Beta
Classifier: Intended Audience :: Developers
Classifier: Intended Audience :: System Administrators
Classifier: License :: OSI Approved :: MIT License
Classifier: Operating System :: OS Independent
Classifier: Programming Language :: Python :: 3
Classifier: Programming Language :: Python :: 3.10
Classifier: Programming Language :: Python :: 3.11
Classifier: Programming Language :: Python :: 3.12
Classifier: Topic :: Software Development :: Libraries :: Python Modules
Classifier: Topic :: System :: Installation/Setup
Classifier: Topic :: Utilities
Classifier: Environment :: Console
Classifier: Typing :: Typed
Requires-Python: >=3.10
License-File: LICENSE
Requires-Dist: click>=8.1.0
Requires-Dist: boto3>=1.34.0
Requires-Dist: rich>=13.7.0
Requires-Dist: python-dotenv>=1.0.0
Provides-Extra: dev
Requires-Dist: pytest>=7.0.0; extra == "dev"
Requires-Dist: pytest-cov>=4.0.0; extra == "dev"
Requires-Dist: pytest-mock>=3.10.0; extra == "dev"
Requires-Dist: black>=23.0.0; extra == "dev"
Requires-Dist: mypy>=1.0.0; extra == "dev"
Requires-Dist: flake8>=6.0.0; extra == "dev"
Requires-Dist: pre-commit>=3.0.0; extra == "dev"
Requires-Dist: bump2version>=1.0.0; extra == "dev"
Requires-Dist: bandit>=1.7.0; extra == "dev"
Requires-Dist: safety>=2.0.0; extra == "dev"
Provides-Extra: test
Requires-Dist: pytest>=7.0.0; extra == "test"
Requires-Dist: pytest-cov>=4.0.0; extra == "test"
Requires-Dist: pytest-mock>=3.10.0; extra == "test"
Requires-Dist: moto[bedrock]>=4.2.0; extra == "test"
Dynamic: author
Dynamic: home-page
Dynamic: license-file
Dynamic: requires-python
